LICENSE
MANIFEST.in
README.rst
VERSION
setup.py
docktors/__init__.py
docktors/core.py
docktors/decorators.py
docktors/wdocker.py
pydocktors.egg-info/PKG-INFO
pydocktors.egg-info/SOURCES.txt
pydocktors.egg-info/dependency_links.txt
pydocktors.egg-info/requires.txt
pydocktors.egg-info/top_level.txt