Metadata-Version: 1.1
Name: pydocktors
Version: 0.0.4
Summary: Simple docker decorator
Home-page: https://github.com/Patouche/pydocktors
Author: Patrick Allain
Author-email: patralla@gmail.com
License: The MIT License (MIT)
Download-URL: https://github.com/Patouche/pydocktors/archive/v0.0.4.tar.gz
Keywords: docker,decorator,testing,example
Platform: UNKNOWN
